charlie/__init__.py
charlie/agent_registry.py
charlie/assets_manager.py
charlie/cli.py
charlie/config_merger.py
charlie/config_reader.py
charlie/enums.py
charlie/markdown_generator.py
charlie/mcp_server_generator.py
charlie/placeholder_transformer.py
charlie/repository_fetcher.py
charlie/schema.py
charlie/tracker.py
charlie/variable_collector.py
charlie/configurators/__init__.py
charlie/configurators/agent_configurator.py
charlie/configurators/agent_configurator_factory.py
charlie/configurators/claude_configurator.py
charlie/configurators/copilot_configurator.py
charlie/configurators/cursor_configurator.py
charlie_agents-0.7.0.dist-info/METADATA
charlie_agents-0.7.0.dist-info/WHEEL
charlie_agents-0.7.0.dist-info/entry_points.txt
charlie_agents-0.7.0.dist-info/licenses/LICENSE
charlie_agents-0.7.0.dist-info/RECORD
