Metadata-Version: 2.4
Name: charlie-agents
Version: 0.7.0
Summary: Universal Agent Config Generator
Project-URL: Homepage, https://github.com/henriquemoody/charlie
Project-URL: Documentation, https://github.com/henriquemoody/charlie#readme
Project-URL: Repository, https://github.com/henriquemoody/charlie
Project-URL: Issues, https://github.com/henriquemoody/charlie/issues
Author-email: Henrique Moody <henriquemoody@gmail.com>
License: MIT
License-File: LICENSE
Keywords: agents,ai,claude,commands,copilot,cursor,mcp,transpiler
Classifier: Development Status :: 4 - Beta
Classifier: Intended Audience :: Developers
Classifier: License :: OSI Approved :: MIT License
Classifier: Programming Language :: Python :: 3
Classifier: Programming Language :: Python :: 3.11
Classifier: Programming Language :: Python :: 3.12
Requires-Python: >=3.11
Requires-Dist: pydantic>=2.0.0
Requires-Dist: python-dotenv>=1.0.0
Requires-Dist: python-slugify<9.0.0,>=8.0.4
Requires-Dist: pyyaml>=6.0.0
Requires-Dist: rich>=13.0.0
Requires-Dist: typer>=0.9.0
Provides-Extra: dev
Requires-Dist: mypy>=1.0.0; extra == 'dev'
Requires-Dist: pytest-cov>=4.0.0; extra == 'dev'
Requires-Dist: pytest>=7.0.0; extra == 'dev'
Requires-Dist: ruff>=0.1.0; extra == 'dev'
